AUTHORS
COPYING
LICENSE
MANIFEST.in
README.markdown
setup.py
gitjobs/__init__.py
gitjobs/core.py
gitjobs/test.py
gitjobs.egg-info/PKG-INFO
gitjobs.egg-info/SOURCES.txt
gitjobs.egg-info/dependency_links.txt
gitjobs.egg-info/top_level.txt