Metadata-Version: 1.0
Name: gitjobs
Version: 0.0.1
Summary: Python binding for github jobs API
Home-page: UNKNOWN
Author: Vasyl Dizhak
Author-email: vasyl.dizhak@djangostars.com
License: MIT
Platform: UNKNOWN
Classifier: License :: OSI Approved :: MIT License
Classifier: Development Status :: 2 - Pre-Alpha
Classifier: Topic :: Software Development :: Libraries :: Python ModulesProgramming Language :: Python
